Metadata-Version: 2.4
Name: codegen-sh
Version: 1.18.1
Summary: Add your description here
Requires-Python: >=3.13
Requires-Dist: algoliasearch
Requires-Dist: click
Requires-Dist: codegen-types>=0.263.0
Requires-Dist: giturlparse
Requires-Dist: graph-sitter-types>=6.2.1
Requires-Dist: pathlib
Requires-Dist: posthog
Requires-Dist: pydantic>=2.10.3
Requires-Dist: pygit2>=1.16.0
Requires-Dist: python-dotenv>=1.0.1
Requires-Dist: requests
Requires-Dist: rich
Requires-Dist: rich-click>=1.8.5
Requires-Dist: toml>=0.10.2
